dumbdown/__init__.py
dumbdown/internals.py
dumbdown-1.0.5.dist-info/LICENSE
dumbdown-1.0.5.dist-info/METADATA
dumbdown-1.0.5.dist-info/WHEEL
dumbdown-1.0.5.dist-info/top_level.txt
dumbdown-1.0.5.dist-info/RECORD
