Metadata-Version: 2.1
Name: dumbdown
Version: 1.0.5
Summary: *Extremely* _simple_ markdown-ish format
Home-page: https://github.com/gojefferson/dumbdown
Author: Jeff Kerr
Author-email: jeff@casefleet.com
License: MIT
Platform: UNKNOWN
Classifier: License :: OSI Approved :: MIT License
Classifier: Programming Language :: Python :: 3
Classifier: Programming Language :: Python :: 3.7
Requires-Python: >= 3.7
